pydictdisplayfilter/__init__.py
pydictdisplayfilter/display_filters.py
pydictdisplayfilter/exceptions.py
pydictdisplayfilter/factories.py
pydictdisplayfilter/helpers.py
pydictdisplayfilter/models.py
pydictdisplayfilter/slicers.py
pydictdisplayfilter/evaluators/__init__.py
pydictdisplayfilter/evaluators/common.py
pydictdisplayfilter/parsers/__init__.py
pydictdisplayfilter/parsers/common.py
pydictdisplayfilter/parsers/display_filter.py
tests/__init__.py
tests/test_csv_display_filter_example.py
tests/test_dict_display_filter.py
tests/test_dict_display_filter_shell.py
tests/test_display_filter_parser.py
tests/test_json_display_filter_example.py
tests/test_nmap_display_filter_example.py
tests/test_object_display_filter.py
tests/test_slicers.py
tests/test_sql_display_filter.py
tests/test_sqlite_display_filter_example.py
tests/test_table.py
python_dict_display_filter-1.2.0.dist-info/LICENSE
python_dict_display_filter-1.2.0.dist-info/METADATA
python_dict_display_filter-1.2.0.dist-info/WHEEL
python_dict_display_filter-1.2.0.dist-info/top_level.txt
python_dict_display_filter-1.2.0.dist-info/RECORD
