Metadata-Version: 2.1
Name: python-dict-display-filter
Version: 1.2.0
Summary: A Wireshark-like display filter for dictionaries.
Home-page: https://github.com/bytebutcher/python-dict-display-filter
Author: bytebutcher
Author-email: thomas.engel.web@gmail.com
License: GPL-3.0
Classifier: Programming Language :: Python :: 3
Classifier: Operating System :: OS Independent
License-File: LICENSE
Requires-Dist: packaging (==23.1)
Requires-Dist: parameterized (==0.8.1)
Requires-Dist: pyparsing (==3.0.6)
Requires-Dist: ipranger (==1.1.2)
Requires-Dist: python-dateutil (==2.8.2)
Provides-Extra: test
Requires-Dist: pytest (==7.3.1) ; extra == 'test'
Requires-Dist: pytest-cov (==4.0.0) ; extra == 'test'
Requires-Dist: pexpect (==4.8.0) ; extra == 'test'
Requires-Dist: python-libnmap (==0.7.0) ; extra == 'test'
